dsbin/__init__.py
dsbin/dev/__init__.py
dsbin/dev/changelogs.py
dsbin/dev/check_dependencies.py
dsbin/dev/check_imports.py
dsbin/dev/code_configs/__init__.py
dsbin/dev/code_configs/code_configs.py
dsbin/dev/impact_analyzer.py
dsbin/dev/package_analyzer.py
dsbin/dev/reporun.py
dsbin/dev/tag_replace.py
dsbin/dsver.py
dsbin/files/__init__.py
dsbin/files/backupsort.py
dsbin/files/bigfiles.py
dsbin/files/dupefinder.py
dsbin/files/foldermerge.py
dsbin/files/rsyncer.py
dsbin/fun/__init__.py
dsbin/fun/wm_adventure.py
dsbin/logic/__init__.py
dsbin/logic/bipclean.py
dsbin/logic/bounce_parser.py
dsbin/logic/bouncefiler.py
dsbin/logic/bounceprune.py
dsbin/logic/bounces.py
dsbin/logic/oldprojects.py
dsbin/lsbin.py
dsbin/mac/__init__.py
dsbin/mac/dmg_encrypt.py
dsbin/mac/dmgify.py
dsbin/mac/netreset.py
dsbin/mac/setmag.py
dsbin/mac/timestamps.py
dsbin/media/__init__.py
dsbin/media/ffgif.py
dsbin/media/fftrim.py
dsbin/media/media_manager.py
dsbin/music/__init__.py
dsbin/music/alacrity.py
dsbin/music/awa.py
dsbin/music/azmusic.py
dsbin/music/hpfilter.py
dsbin/music/metacopy.py
dsbin/music/mp3ify.py
dsbin/music/mshare.py
dsbin/music/rmp3.py
dsbin/pybounce/__init__.py
dsbin/pybounce/bounce_files.py
dsbin/pybounce/client_protocol.py
dsbin/pybounce/main.py
dsbin/pybounce/sqlite_manager.py
dsbin/pybumper/README.md
dsbin/pybumper/__init__.py
dsbin/pybumper/bump_type.py
dsbin/pybumper/git_helper.py
dsbin/pybumper/main.py
dsbin/pybumper/version_helper.py
dsbin/pyprojector/__init__.py
dsbin/pyprojector/pypi_classifiers.py
dsbin/pyprojector/pyprojector.py
dsbin/systemd/__init__.py
dsbin/systemd/service_list.py
dsbin/systemd/systemd.py
dsbin/text/__init__.py
dsbin/text/csvfix.py
dsbin/text/pycompare.py
dsbin/text/w11renamer.py
dsbin/text/wrapper.py
dsbin/tools/__init__.py
dsbin/tools/changehostname.py
dsbin/tools/dockermounter.py
dsbin/tools/dsfish.py
dsbin/tools/dsservice.py
dsbin/tools/envsync.py
dsbin/tools/install_packages.py
dsbin/tools/spacepurger.py
dsbin/tools/ssh_tunnel.py
dsbin-0.9.9.dist-info/METADATA
dsbin-0.9.9.dist-info/WHEEL
dsbin-0.9.9.dist-info/entry_points.txt
dsbin-0.9.9.dist-info/licenses/LICENSE
dsbin-0.9.9.dist-info/RECORD
