Metadata-Version: 2.4
Name: dsbin
Version: 0.9.9
Summary: Personal script library solving problems you didn't know you cared about
License-Expression: LGPL-3.0-or-later
License-File: LICENSE
Author: Danny Stewart
Author-email: danny@stewart.cc
Requires-Python: >=3.12,<4.0
Classifier: Development Status :: 4 - Beta
Classifier: Intended Audience :: Developers
Classifier: Intended Audience :: End Users/Desktop
Classifier: Intended Audience :: Information Technology
Classifier: Intended Audience :: System Administrators
Classifier: License :: OSI Approved :: GNU General Public License v3 or later (GPLv3+)
Classifier: Programming Language :: Python :: 3
Classifier: Programming Language :: Python :: 3.12
Classifier: Programming Language :: Python :: 3.13
Classifier: Topic :: Communications :: File Sharing
Classifier: Topic :: Multimedia :: Sound/Audio
Classifier: Topic :: Multimedia :: Sound/Audio :: Conversion
Classifier: Topic :: Multimedia :: Video
Classifier: Topic :: Multimedia :: Video :: Conversion
Classifier: Topic :: Software Development :: Libraries
Classifier: Topic :: Software Development :: Libraries :: Python Modules
Classifier: Topic :: System :: Shells
Classifier: Topic :: System :: System Shells
Classifier: Topic :: Utilities
Requires-Dist: azure-storage-blob (>=12.27.1)
Requires-Dist: blessed (>=1.25.0)
Requires-Dist: chardet (>=5.2.0)
Requires-Dist: halo (>=0.0.31)
Requires-Dist: inquirer (>=3.4.1)
Requires-Dist: mutagen (>=1.47.0)
Requires-Dist: mysql-connector-python (>=9.5.0)
Requires-Dist: natsort (>=8.4.0)
Requires-Dist: numpy (>=2.3.5)
Requires-Dist: packaging (>=25.0)
Requires-Dist: paramiko (>=4.0.0)
Requires-Dist: pexpect (>=4.9.0)
Requires-Dist: pillow (>=12.0.0)
Requires-Dist: polykit (>=0.14.6)
Requires-Dist: prompt-toolkit (>=3.0.52)
Requires-Dist: pydub (>=0.25.1)
Requires-Dist: pyperclip (>=1.11.0)
Requires-Dist: requests (>=2.32.5)
Requires-Dist: rich (>=14.2.0)
Requires-Dist: rsa (>=4.9.1)
Requires-Dist: scipy (>=1.16.3)
Requires-Dist: scp (>=0.15.0)
Requires-Dist: telethon (>=1.42.0)
Requires-Dist: tomli-w (>=1.2.0)
Requires-Dist: tomlkit (>=0.13.3)
Requires-Dist: tqdm (>=4.67.1)
Requires-Dist: types-paramiko (>=4.0.0.20250822)
Requires-Dist: types-pillow (>=10.2.0.20240822)
Requires-Dist: types-requests (>=2.32.4.20250913)
Project-URL: Repository, https://github.com/dannystewart/dsbin
